emma/__init__.py
emma/analysis.py
emma/elements.py
emma/elemlib.py
emma/graphics.py
emma/materials.py
emma/matlib.py
emma/matrices.py
emma/objects.py
emma/solvers.py
emma/data/Cape Mendocino.dat
emma/data/ChiChi.dat
emma/data/El Centro.dat
emma/data/Hollister.dat
emma/data/Imperial Valley.dat
emma/data/Kobe.dat
emma/data/Kocaeli.dat
emma/data/Loma Prieta.dat
emma/data/Northridge.dat
emma/data/San Fernando.dat
emma/data/Spitak.dat
emma/data/elcentro.dat
emma/seismic/RotD50.csv
emma/utilities/__init__.py
emma/utilities/export.py
emma/utilities/import.py
emma/utilities/ipyutils.py
emma/utilities/matrices.py
emma/utilities/numerical.py
emma/utilities/tensor.py
emma/utilities/fedeas/__init__.py
emma/utilities/numeric/__init__.py
emma/utilities/numeric/integrate.py
emma/utilities/numeric/quadrature.py
emma/utilities/numeric/roots.py
emme-0.0.0.dist-info/METADATA
emme-0.0.0.dist-info/WHEEL
emme-0.0.0.dist-info/top_level.txt
emme-0.0.0.dist-info/RECORD
